keydnn/__init__.py
keydnn/activations.py
keydnn/conv_utils.py
keydnn/layers.py
keydnn/losses.py
keydnn/models.py
keydnn/threading_utils.py
keydnn/utilities.py
keydnn/bin/conv_lib_linux.so
keydnn/bin/conv_lib_windows.dll
KeyDnn-0.16.3.dist-info/LICENSE
KeyDnn-0.16.3.dist-info/METADATA
KeyDnn-0.16.3.dist-info/WHEEL
KeyDnn-0.16.3.dist-info/top_level.txt
KeyDnn-0.16.3.dist-info/RECORD
